salabim/DejaVuSansMono.ttf
salabim/LICENSE.txt
salabim/__init__.py
salabim/calibri.ttf
salabim/mplus-1m-regular.ttf
salabim/salabim.py
salabim-25.0.14.dist-info/METADATA
salabim-25.0.14.dist-info/WHEEL
salabim-25.0.14.dist-info/top_level.txt
salabim-25.0.14.dist-info/RECORD
