Metadata-Version: 2.4
Name: salabim
Version: 25.0.14
Summary: salabim - discrete event simulation in Python
Author-email: Ruud van der Ham <rt.van.der.ham@gmail.com>
Project-URL: Homepage, https://salabim.org
Project-URL: Repository, https://github.com/salabim/salabim
Classifier: Development Status :: 5 - Production/Stable
Classifier: License :: OSI Approved :: MIT License
Classifier: Programming Language :: Python :: 3 :: Only
Requires-Python: >=3.7
